setuptools_pipfile/__init__.py
setuptools_pipfile/keyword.py
setuptools_pipfile/pipfile.py
setuptools_pipfile-0.7.0.dist-info/LICENSE
setuptools_pipfile-0.7.0.dist-info/METADATA
setuptools_pipfile-0.7.0.dist-info/WHEEL
setuptools_pipfile-0.7.0.dist-info/entry_points.txt
setuptools_pipfile-0.7.0.dist-info/top_level.txt
setuptools_pipfile-0.7.0.dist-info/zip-safe
setuptools_pipfile-0.7.0.dist-info/RECORD
