Metadata-Version: 2.1
Name: setuptools-pipfile
Version: 0.7.0
Summary: Dependency management via Pipfile
Home-page: https://github.com/asyncon/setuptools-pipfile
Author: asyncon
Author-email: 53700266+asyncon@users.noreply.github.com
License: MIT
Project-URL: Bug Tracker, https://github.com/asyncon/setuptools-pipfile/issues
Project-URL: Documentation, https://setuptools-pipfile.readthedocs.io
Project-URL: Source Code, https://github.com/asyncon/setuptools-pipfile
Platform: UNKNOWN
Classifier: Development Status :: 4 - Beta
Classifier: Intended Audience :: Developers
Classifier: Framework :: Setuptools Plugin
Classifier: License :: OSI Approved :: MIT License
Classifier: Operating System :: OS Independent
Classifier: Programming Language :: Python
Classifier: Programming Language :: Python :: 3
Classifier: Programming Language :: Python :: 3.4
Classifier: Programming Language :: Python :: 3.5
Classifier: Programming Language :: Python :: 3.6
Classifier: Programming Language :: Python :: 3.7
Classifier: Programming Language :: Python :: 3.8
Classifier: Programming Language :: Python :: 3.9
Classifier: Programming Language :: Python :: 3.10
License-File: LICENSE
Requires-Dist: toml
Provides-Extra: docs
Requires-Dist: mkdocs-material ; extra == 'docs'
